apeye_core/__init__.py
apeye_core/_tld.py
apeye_core/email_validator.py
apeye_core/public_suffix_list.dat
apeye_core/py.typed
apeye_core-1.1.3.dist-info/METADATA
apeye_core-1.1.3.dist-info/WHEEL
apeye_core-1.1.3.dist-info/licenses/LICENSE
apeye_core-1.1.3.dist-info/RECORD
