Metadata-Version: 2.1
Name: apeye-core
Version: 1.1.3
Summary: Core (offline) functionality for the apeye library.
Project-URL: Homepage, https://github.com/domdfcoding/apeye-core
Project-URL: Issue Tracker, https://github.com/domdfcoding/apeye-core/issues
Project-URL: Source Code, https://github.com/domdfcoding/apeye-core
Author-email: Dominic Davis-Foster <dominic@davis-foster.co.uk>
License: Copyright (c) 2022, Dominic Davis-Foster
License-File: LICENSE
Keywords: url
Classifier: Development Status :: 5 - Production/Stable
Classifier: Intended Audience :: Developers
Classifier: License :: OSI Approved :: BSD License
Classifier: Operating System :: OS Independent
Classifier: Programming Language :: Python
Classifier: Programming Language :: Python :: 3 :: Only
Classifier: Programming Language :: Python :: 3.6
Classifier: Programming Language :: Python :: 3.7
Classifier: Programming Language :: Python :: 3.8
Classifier: Programming Language :: Python :: 3.9
Classifier: Programming Language :: Python :: 3.10
Classifier: Programming Language :: Python :: 3.11
Classifier: Programming Language :: Python :: Implementation :: CPython
Classifier: Programming Language :: Python :: Implementation :: PyPy
Classifier: Topic :: Software Development :: Libraries :: Python Modules
Classifier: Typing :: Typed
Requires-Python: >=3.6.1
Requires-Dist: domdf-python-tools>=2.6.0
Requires-Dist: idna>=2.5
